{
  "dataset": {
    "identifier": 107873,
    "name": "s2_20211104_0001_3233_01",
    "src_path": "/data/file/cubeManager/PROJECT018/39/txt20211101110642040481/s2_20211104_0001_3233_01/",
    "label_path": "/data/file/cubeManager/PROJECT018/39/txt20211101110642040481/s2_20211104_0001_3233_01/",
    "category": 2,
    "type": 0
  },
  "licenses": {
    "name": "Apache License 1.0",
    "url": "http://www.apache.org/licenses/LICENSE-1.0"
  },
  "info": [
    {
      "id": 115073,
      "filename": "s2_20211001_0019_0012_01.txt",
      "title": "s2_20211001_0019_0012_01",
      "mediatype": "콜센터",
      "medianame": "콜센터",
      "category": "목적대화",
      "date": "2021-11-01",
      "size": 329,
      "annotations": {
        "subject": "제품/사용문의",
        "speaker_type": "1:1",
        "size": 329,
        "word_size": 77,
        "text": "A.반갑습니다 #@소속# 고객센터 #@이름# 입니다\nB.안녕하세요 제가 반려 동물과 투숙이 하고 싶어요\nA.예 지금 이미 예약을 하신 상태이신가요\nB.아니요 가능한지 아닌지를 몰라서요\nA.각 호텔의 반려 동물 동반 규정에 따라 상이합니다\nB.상이하다가 무슨 말이에요\nA.일부 호텔의 경우에만 가능하십니다\nB.그래요 반려 동물 가능이라고 써있는 곳으로 하면 되죠\nA.예약하시기 전에 호텔 프론트에 전화 부탁 드립니다\nB.프론트에 제가 직접이오\nA.죄송하지만 반려동물의 범주가 너무 넓으셔서요\nA.예방 접종 여부 등 변수가 너무 많습니다\nB.어쩔 수 없네요 알았어요\nA.도움을 못 드려 죄송합니다 #@소속# 였습니다",
        "lines": [
          {
            "id": 1,
            "text": "A.반갑습니다 #@소속# 고객센터 #@이름# 입니다",
            "norm_text": "A.반갑습니다 #@소속# 고객센터 #@이름# 입니다",
            "speaker": {
              "id": "A",
              "sex": "여성",
              "age": "2그룹(30대~40대)"
            },
            "speechAct": "인사하기",
            "morpheme": "A/SL+반갑/VA+습니다/EF+#/SY+@/SY+소속/NNG+#/SY+고객/NNG+센터/NNG+#/SY+@/SY+이름/NNG+#/SY+입니다/VCP+EC"
          },
          {
            "id": 2,
            "text": "B.안녕하세요 제가 반려 동물과 투숙이 하고 싶어요",
            "norm_text": "B.안녕하세요 제가 반려 동물과 투숙이 하고 싶어요",
            "speaker": {
              "id": "B",
              "sex": "여성",
              "age": "2그룹(30대~40대)"
            },
            "speechAct": "진술하기",
            "morpheme": "B/SL+./SY+안녕/NNG+하/XSV+세요/EP+EF+제/NP+가/JKS+반려/NNG+동물/NNG+과/JC+투숙/NNG+이/JKS+하/VV+고/EC+싶/VX+어요/EF"
          },
          {
            "id": 3,
            "text": "A.예 지금 이미 예약을 하신 상태이신가요",
            "norm_text": "A.예 지금 이미 예약을 하신 상태이신가요",
            "speaker": {
              "id": "A",
              "sex": "여성",
              "age": "2그룹(30대~40대)"
            },
            "speechAct": "질문하기",
            "morpheme": "A/SL+예/IC+지금/MAG+이미/MAG+예약/NNG+을/JKO+하/VV+신/EP+ETM+상태/NNG+이/VCP+신가요/EP+EC"
          },
          {
            "id": 4,
            "text": "B.아니요 가능한지 아닌지를 몰라서요",
            "norm_text": "B.아니요 가능한지 아닌지를 몰라서요",
            "speaker": {
              "id": "B",
              "sex": "여성",
              "age": "2그룹(30대~40대)"
            },
            "speechAct": "진술하기",
            "morpheme": "B/SL+아니요/IC+가능/NNG+한지/XSA+EC+아닌지/VCN+EC+를/JKO+몰/VV+라서요/EC"
          },
          {
            "id": 5,
            "text": "A.각 호텔의 반려 동물 동반 규정에 따라 상이합니다",
            "norm_text": "A.각 호텔의 반려 동물 동반 규정에 따라 상이합니다",
            "speaker": {
              "id": "A",
              "sex": "여성",
              "age": "2그룹(30대~40대)"
            },
            "speechAct": "진술하기",
            "morpheme": "A/SL+각/MM+호텔/NNG+의/JKG+반려/NNG+동물/NNG+동반/NNG+규정/NNG+에/JKB+따라/VV+EC+상이/XR+합니다/XSA+EC"
          },
          {
            "id": 6,
            "text": "B.상이하다가 무슨 말이에요",
            "norm_text": "B.상이하다가 무슨 말이에요",
            "speaker": {
              "id": "B",
              "sex": "여성",
              "age": "2그룹(30대~40대)"
            },
            "speechAct": "질문하기",
            "morpheme": "B/SL+상이/XR+하/XSA+다가/EC+무슨/MM+말/NNG+이/VCP+에요/EF"
          },
          {
            "id": 7,
            "text": "A.일부 호텔의 경우에만 가능하십니다",
            "norm_text": "A.일부 호텔의 경우에만 가능하십니다",
            "speaker": {
              "id": "A",
              "sex": "여성",
              "age": "2그룹(30대~40대)"
            },
            "speechAct": "진술하기",
            "morpheme": "A/SL+./SY+일부/NNG+호텔/NNG+의/JKG+경우/NNG+에/JKB+만/JX+가능/NNG+하/XSV+십니다/EP+EC"
          },
          {
            "id": 8,
            "text": "B.그래요 반려 동물 가능이라고 써있는 곳으로 하면 되죠",
            "norm_text": "B.그래요 반려 동물 가능이라고 써있는 곳으로 하면 되죠",
            "speaker": {
              "id": "B",
              "sex": "여성",
              "age": "2그룹(30대~40대)"
            },
            "speechAct": "질문하기",
            "morpheme": "B/SL+그래요/VV+EF+반려/NNG+동물/NNG+가능/NNG+이/VCP+라고/EC+써/VV+EC+있/VX+는/ETM+곳/NNG+으로/JKB+하/VV+면/EC+되/VV+죠/EC"
          },
          {
            "id": 9,
            "text": "A.예약하시기 전에 호텔 프론트에 전화 부탁 드립니다",
            "norm_text": "A.예약하시기 전에 호텔 프론트에 전화 부탁 드립니다",
            "speaker": {
              "id": "A",
              "sex": "여성",
              "age": "2그룹(30대~40대)"
            },
            "speechAct": "부탁하기",
            "morpheme": "A/SL+./SY+예약/NNG+하/XSV+시/EP+기/ETN+전/NNG+에/JKB+호텔/NNG+프론트/NNP+에/JKB+전화/NNG+부탁/NNG+드립니다/VV+EC"
          },
          {
            "id": 10,
            "text": "B.프론트에 제가 직접이오",
            "norm_text": "B.프론트에 제가 직접이오",
            "speaker": {
              "id": "B",
              "sex": "여성",
              "age": "2그룹(30대~40대)"
            },
            "speechAct": "질문하기",
            "morpheme": "B/SL+./SY+프론트/NNP+에/JKB+제/NP+가/JKS+직접/MAG+이오/NNG"
          },
          {
            "id": 11,
            "text": "A.죄송하지만 반려동물의 범주가 너무 넓으셔서요",
            "norm_text": "A.죄송하지만 반려동물의 범주가 너무 넓으셔서요",
            "speaker": {
              "id": "A",
              "sex": "여성",
              "age": "2그룹(30대~40대)"
            },
            "speechAct": "진술하기",
            "morpheme": "A/SL+죄송/XR+하/XSA+지만/EC+반려/NNG+동물/NNG+의/JKG+범주/NNG+가/JKS+너무/MAG+넓/VA+으셔서/EP+EC+요/JX"
          },
          {
            "id": 12,
            "text": "A.예방 접종 여부 등 변수가 너무 많습니다",
            "norm_text": "A.예방 접종 여부 등 변수가 너무 많습니다",
            "speaker": {
              "id": "A",
              "sex": "여성",
              "age": "2그룹(30대~40대)"
            },
            "speechAct": "진술하기",
            "morpheme": "A/SL+./SY+예방/NNG+접종/NNG+여부/NNG+등/NNB+변수/NNG+가/JKS+너무/MAG+많/VA+습니다/EF"
          },
          {
            "id": 13,
            "text": "B.어쩔 수 없네요 알았어요",
            "norm_text": "B.어쩔 수 없네요 알았어요",
            "speaker": {
              "id": "B",
              "sex": "여성",
              "age": "2그룹(30대~40대)"
            },
            "speechAct": "진술하기",
            "morpheme": "B/SL+어쩔/VV+ETM+수/NNB+없/VA+네요/EC+알/VV+았/EP+어요/EF"
          },
          {
            "id": 14,
            "text": "A.도움을 못 드려 죄송합니다 #@소속# 였습니다",
            "norm_text": "A.도움을 못 드려 죄송합니다 #@소속# 였습니다",
            "speaker": {
              "id": "A",
              "sex": "여성",
              "age": "2그룹(30대~40대)"
            },
            "speechAct": "사과하기",
            "morpheme": "A/SL+./SY+도움/NNG+을/JKO+못/MAG+드려/VV+EC+죄송/XR+합니다/XSA+EF+#/SY+@/SY+소속/NNG+#/SY+였/VCP+EP+습니다/EF"
          }
        ]
      }
    }
  ]
}