{
  "dataset": {
    "identifier": 89965,
    "name": "INSTAGRAM_248_05_set",
    "src_path": "/data/file/cubeManager/PROJECT001/64/txt202110291517260735104/INSTAGRAM_248_05_set/",
    "label_path": "/data/file/cubeManager/PROJECT001/64/txt202110291517260735104/INSTAGRAM_248_05_set/",
    "category": 2,
    "type": 0
  },
  "licenses": {
    "name": "Apache License 1.0",
    "url": "http://www.apache.org/licenses/LICENSE-1.0"
  },
  "info": [
    {
      "id": 109945,
      "filename": "INSTAGRAM_248_05.txt",
      "title": "INSTAGRAM_248_05",
      "mediatype": "SNS",
      "medianame": "인스타그램",
      "category": "일상대화",
      "date": "2021-10-29",
      "size": 502,
      "annotations": {
        "subject": "군대",
        "speaker_type": "다자간 대화",
        "size": 502,
        "word_size": 138,
        "text": "1 : **아 너 군악대 출신이지?\n2 : 응~ 나 해군 군악대 나왔어\n3 : 해군이었어? 해군 군악대는 합격하기 힘들다고 하던데 대단하네~\n1 : 오~ 그렇구나. 경쟁률이 좀 높은가?\n2 : 지금은 모르겠는데 나 시험 봤을 때 400:1 정도였어. 통계를 봤거든^^\n3 : 400:1 ? 장난아니네~ 무슨 군대를 경쟁을 뚫고 들어가냐\n1 : 그러게; 그러면 해군 군악대는 들어가면 생활이 어때? 편해?\n2 : 뭐. 일단 기본적인 훈련은 거의 열외야~ 행사부대이다보니 행사에 집중하지~\n3 : 그러면 편한거 아니야? 훈련을 거의 안 받는다고 하면?\n1 : 외부에서는 그렇게 봐도 내부에서는 다른 상황인건가?\n2 : 그렇지! 편해 보여도 가혹행위도 많고 엄청 맞기도 하지~\n3 : 구타와 가혹행위가 있다는 거야? 그러면 헌병대에서 단속 안 해?\n1 : 그러게~ 헌병은 그런 역할도 하잖아~\n2 : 군악대는 보통 군악대대 라고 해서 타 병과에 정보가 유출되지 않아.\n3 : 그렇구나. 많이 맞기도 하는구나... 생각도 못했어.",
        "lines": [
          {
            "id": 1,
            "text": "1 : **아 너 군악대 출신이지?",
            "norm_text": "**아 너 군악대 출신이지?",
            "speaker": {
              "id": "1번",
              "sex": "여성",
              "age": "40대"
            },
            "speechAct": "(지시) 질문하기",
            "morpheme": "*/SY+*/SY+아/IC+너/NP+군악대/NNG+출신/NNG+이/VCP+지/EF"
          },
          {
            "id": 2,
            "text": "2 : 응~ 나 해군 군악대 나왔어",
            "norm_text": "응~ 나 해군 군악대 나왔어",
            "speaker": {
              "id": "2번",
              "sex": "남성",
              "age": "30대"
            },
            "speechAct": "(단언) 진술하기",
            "morpheme": "응/IC+~/SY+나/JX+해군/NNG+군악대/NNG+나왔/VV+EP+어/EC"
          },
          {
            "id": 3,
            "text": "3 : 해군이었어? 해군 군악대는 합격하기 힘들다고 하던데 대단하네~",
            "norm_text": "해군이었어? 해군 군악대는 합격하기 힘들다고 하던데 대단하네~",
            "speaker": {
              "id": "3번",
              "sex": "여성",
              "age": "30대"
            },
            "speechAct": "(단언) 주장하기",
            "morpheme": "해군/NNG+이/VCP+었/EP+어/EF+해군/NNG+군악대/NNG+는/JX+합격/NNG+하/XSV+기/ETN+힘들/VA+다고/EC+하/VV+던데/EC+대단/XR+하/XSA+네/EF+~/SY"
          },
          {
            "id": 4,
            "text": "1 : 오~ 그렇구나. 경쟁률이 좀 높은가?",
            "norm_text": "오~ 그렇구나. 경쟁률이 좀 높은가?",
            "speaker": {
              "id": "1번",
              "sex": "여성",
              "age": "40대"
            },
            "speechAct": "(단언) 주장하기",
            "morpheme": "오/NR+~/SY+그렇/VA+구나/EF+경쟁/NNG+률/XSN+이/JKS+좀/MAG+높/VA+은가/EF"
          },
          {
            "id": 5,
            "text": "2 : 지금은 모르겠는데 나 시험 봤을 때 400:1 정도였어. 통계를 봤거든^^",
            "norm_text": "지금은 모르겠는데 나 시험 봤을 때 400:1 정도였어. 통계를 봤거든^^",
            "speaker": {
              "id": "2번",
              "sex": "남성",
              "age": "30대"
            },
            "speechAct": "(단언) 진술하기",
            "morpheme": "지금/MAG+은/JX+모르/VV+겠/EP+는데/EC+나/NP+시험/NNG+봤/VV+EP+을/ETM+때/NNG+400/SN+:/SC+1/SN+정도/NNG+였/VCP+EP+어/EF+통계/NNG+를/JKO+봤/VV+EP+거든/EF+^/SY+^/SY"
          },
          {
            "id": 6,
            "text": "3 : 400:1 ? 장난아니네~ 무슨 군대를 경쟁을 뚫고 들어가냐",
            "norm_text": "400:1 ? 장난아니네~ 무슨 군대를 경쟁을 뚫고 들어가냐",
            "speaker": {
              "id": "3번",
              "sex": "여성",
              "age": "30대"
            },
            "speechAct": "(단언) 반박하기",
            "morpheme": "400/SN+:/SC+1/SN+장난/NNG+아니/VCN+네/EC+~/SY+무슨/MM+군대/NNG+를/JKO+경쟁/NNG+을/JKO+뚫/VV+고/EC+들어가/VV+냐/EC"
          },
          {
            "id": 7,
            "text": "1 : 그러게; 그러면 해군 군악대는 들어가면 생활이 어때? 편해?",
            "norm_text": "그러게; 그러면 해군 군악대는 들어가면 생활이 어때? 편해?",
            "speaker": {
              "id": "1번",
              "sex": "여성",
              "age": "40대"
            },
            "speechAct": "(지시) 질문하기",
            "morpheme": "그러/VV+게/EC+;/SY+그러면/MAJ+해군/NNG+군악대/NNG+는/JX+들어가/VV+면/EC+생활/NNG+이/JKS+어때/VA+EF+편해/VA+EF"
          },
          {
            "id": 8,
            "text": "2 : 뭐. 일단 기본적인 훈련은 거의 열외야~ 행사부대이다보니 행사에 집중하지~",
            "norm_text": "뭐. 일단 기본적인 훈련은 거의 열외야~ 행사부대이다보니 행사에 집중하지~",
            "speaker": {
              "id": "2번",
              "sex": "남성",
              "age": "30대"
            },
            "speechAct": "(단언) 진술하기",
            "morpheme": "뭐/IC+일단/MAG+기본/NNG+적/XSN+인/VCP+ETM+훈련/NNG+은/JX+거의/MAG+열외/NNG+야/JKV+~/SY+행사/NNG+부대/NNG+이/VCP+다/EC+보/VX+니/EC+행사/NNG+에/JKB+집중/NNG+하/XSV+지/EC+~/SY"
          },
          {
            "id": 9,
            "text": "3 : 그러면 편한거 아니야? 훈련을 거의 안 받는다고 하면?",
            "norm_text": "그러면 편한거 아니야? 훈련을 거의 안 받는다고 하면?",
            "speaker": {
              "id": "3번",
              "sex": "여성",
              "age": "30대"
            },
            "speechAct": "(지시) 질문하기",
            "morpheme": "그러면/MAJ+편한/VA+ETM+거/NNB+아니/VCN+야/EF+훈련/NNG+을/JKO+거의/MAG+안/MAG+받/VV+는다고/EC+하/VV+면/EC"
          },
          {
            "id": 10,
            "text": "1 : 외부에서는 그렇게 봐도 내부에서는 다른 상황인건가?",
            "norm_text": "외부에서는 그렇게 봐도 내부에서는 다른 상황인건가?",
            "speaker": {
              "id": "1번",
              "sex": "여성",
              "age": "40대"
            },
            "speechAct": "(지시) 질문하기",
            "morpheme": "외부/NNG+에서/JKB+는/JX+그렇/VA+게/EC+봐도/VX+EC+내부/NNP+에서/JKB+는/JX+다른/MM+상황/NNG+인/VCP+ETM+건가/NNB+VCP+EF"
          },
          {
            "id": 11,
            "text": "2 : 그렇지! 편해 보여도 가혹행위도 많고 엄청 맞기도 하지~",
            "norm_text": "그렇지! 편해 보여도 가혹행위도 많고 엄청 맞기도 하지~",
            "speaker": {
              "id": "2번",
              "sex": "남성",
              "age": "30대"
            },
            "speechAct": "(단언) 주장하기",
            "morpheme": "그렇/VA+지/EF+편해/VA+EC+보여도/VV+EC+가혹/NNG+행위/NNG+도/JX+많/VA+고/EC+엄청/MAG+맞/VV+기/ETN+도/JX+하/VV+지/EC+~/SY"
          },
          {
            "id": 12,
            "text": "3 : 구타와 가혹행위가 있다는 거야? 그러면 헌병대에서 단속 안 해?",
            "norm_text": "구타와 가혹행위가 있다는 거야? 그러면 헌병대에서 단속 안 해?",
            "speaker": {
              "id": "3번",
              "sex": "여성",
              "age": "30대"
            },
            "speechAct": "(지시) 질문하기",
            "morpheme": "구타/NNG+와/JC+가혹/NNG+행위/NNG+가/JKS+있/VA+다는/ETM+거/NNB+야/VCP+EF+그러면/MAJ+헌병대/NNG+에서/JKB+단속/NNG+안/MAG+해/VV+EF"
          },
          {
            "id": 13,
            "text": "1 : 그러게~ 헌병은 그런 역할도 하잖아~",
            "norm_text": "그러게~ 헌병은 그런 역할도 하잖아~",
            "speaker": {
              "id": "1번",
              "sex": "여성",
              "age": "40대"
            },
            "speechAct": "(단언) 주장하기",
            "morpheme": "그러/VV+게/EC+~/SY+헌병/NNG+은/JX+그런/MM+역할/NNG+도/JX+하/VV+잖아/EC+~/SY"
          },
          {
            "id": 14,
            "text": "2 : 군악대는 보통 군악대대 라고 해서 타 병과에 정보가 유출되지 않아.",
            "norm_text": "군악대는 보통 군악대대 라고 해서 타 병과에 정보가 유출되지 않아.",
            "speaker": {
              "id": "2번",
              "sex": "남성",
              "age": "30대"
            },
            "speechAct": "(지시) 충고/제안하기",
            "morpheme": "군악대는보통군악대대라고해서타병과에정보가유출되지않아/UNKNOWN"
          },
          {
            "id": 15,
            "text": "3 : 그렇구나. 많이 맞기도 하는구나... 생각도 못했어.",
            "norm_text": "그렇구나. 많이 맞기도 하는구나... 생각도 못했어.",
            "speaker": {
              "id": "3번",
              "sex": "여성",
              "age": "30대"
            },
            "speechAct": "(단언) 진술하기",
            "morpheme": "그렇/VA+구나/EF+많이/MAG+맞/VV+기/ETN+도/JX+하/VV+는구나/EF+./SY+생각/NNG+도/JX+못/MAG+했/VV+EP+어/EF"
          }
        ]
      }
    }
  ]
}