{
  "dataset": {
    "identifier": 113599,
    "name": "INSTAGRAM_72_07_set",
    "src_path": "/data/file/cubeManager/PROJECT001/80/txt20211102165120093033/INSTAGRAM_72_07_set/",
    "label_path": "/data/file/cubeManager/PROJECT001/80/txt20211102165120093033/INSTAGRAM_72_07_set/",
    "category": 2,
    "type": 0
  },
  "licenses": {
    "name": "Apache License 1.0",
    "url": "http://www.apache.org/licenses/LICENSE-1.0"
  },
  "info": [
    {
      "id": 131479,
      "filename": "INSTAGRAM_72_07.txt",
      "title": "INSTAGRAM_72_07",
      "mediatype": "SNS",
      "medianame": "인스타그램",
      "category": "일상대화",
      "date": "2021-11-02",
      "size": 464,
      "annotations": {
        "subject": "가족",
        "speaker_type": "1:1",
        "size": 464,
        "word_size": 160,
        "text": "1 : 오빠네는 사촌들이랑 친해?\n1 : 아니면 연락도 안 해?\n2 : 우리 명절 인사는 하고 지내 키키\n1 : 그렇구나\n1 : 오빠네는 그러면 명절 때 친가 외가 다 가?\n2 : 아니\n2 : 우리는 친가만 가 키키\n1 : 그렇구나\n1 : 왜 외가는 안 가?\n2 : 멀어 가지고 아빠가 안 가더라고 키키\n2 : 너무하지?\n1 : 헐 대박 외가집 지역이 어디인데?\n2 : 경기도 양평 키키 명절에 가기엔 좀 무리야\n1 : 아 양평 키키 양평은 진짜 마음먹고 가야겠다!\n2 : 어 근데 안 가주니까 엄마가 우울해 하지 키키\n1 : 그니까 오빠가 어무니 모시고 가!\n2 : 그러고 싶은데 불효자는 웁니다 키키\n1 : 키키 할 ㅜㅜ 그래도 더 늦기 전에 내년 설에는 가 봐!\n2 : 아니야\n2 : 그냥 명절 말고 그전에 갔다 올게 키키\n1 : 키키 오 좋은 생각이다\n1 : 우리는 외가 어르신들 다 돌아가서 갈 고향이 없어,\n2 : 아 엄마가 그럼 명절에 외로워 하시겠네 ㅠㅠ",
        "lines": [
          {
            "id": 1,
            "text": "1 : 오빠네는 사촌들이랑 친해?",
            "norm_text": "오빠네는 사촌들이랑 친해?",
            "speaker": {
              "id": "1번",
              "sex": "여성",
              "age": "20대"
            },
            "speechAct": "(지시) 질문하기",
            "morpheme": "오빠/NNG+네/XSN+는/JX+사촌/NNG+들/XSN+이랑/JKB+친해/VA+EF"
          },
          {
            "id": 2,
            "text": "1 : 아니면 연락도 안 해?",
            "norm_text": "아니면 연락도 안 해?",
            "speaker": {
              "id": "1번",
              "sex": "여성",
              "age": "20대"
            },
            "speechAct": "(지시) 질문하기",
            "morpheme": "아니면/MAJ+연락/NNG+도/JX+안/MAG+해/VV+EF"
          },
          {
            "id": 3,
            "text": "2 : 우리 명절 인사는 하고 지내 키키",
            "norm_text": "우리 명절 인사는 하고 지내 키키",
            "speaker": {
              "id": "2번",
              "sex": "남성",
              "age": "20대"
            },
            "speechAct": "(단언) 주장하기",
            "morpheme": "우리/NP+명절/NNG+인사/NNG+는/JX+하/VV+고/EC+지내/VV+EC+키/NNG+키/XSV+ETN"
          },
          {
            "id": 4,
            "text": "1 : 그렇구나",
            "norm_text": "그렇구나",
            "speaker": {
              "id": "1번",
              "sex": "여성",
              "age": "20대"
            },
            "speechAct": "턴토크 사인(관습적 반응)",
            "morpheme": "그렇/VA+구나/EC"
          },
          {
            "id": 5,
            "text": "1 : 오빠네는 그러면 명절 때 친가 외가 다 가?",
            "norm_text": "오빠네는 그러면 명절 때 친가 외가 다 가?",
            "speaker": {
              "id": "1번",
              "sex": "여성",
              "age": "20대"
            },
            "speechAct": "(지시) 질문하기",
            "morpheme": "오빠/NNG+네/XSN+는/JX+그러/VV+면/EC+명절/NNG+때/NNG+친가/NNG+외가/NNG+다가/JKB+JX+JKS"
          },
          {
            "id": 6,
            "text": "2 : 아니",
            "norm_text": "아니",
            "speaker": {
              "id": "2번",
              "sex": "남성",
              "age": "20대"
            },
            "speechAct": "(단언) 진술하기",
            "morpheme": "아니/IC"
          },
          {
            "id": 7,
            "text": "2 : 우리는 친가만 가 키키",
            "norm_text": "우리는 친가만 가 키키",
            "speaker": {
              "id": "2번",
              "sex": "남성",
              "age": "20대"
            },
            "speechAct": "(단언) 진술하기",
            "morpheme": "우리/NP+는/JX+친가/NNG+만/JX+가/JKS+키/NNG+키/XSV+ETN"
          },
          {
            "id": 8,
            "text": "1 : 그렇구나",
            "norm_text": "그렇구나",
            "speaker": {
              "id": "1번",
              "sex": "여성",
              "age": "20대"
            },
            "speechAct": "턴토크 사인(관습적 반응)",
            "morpheme": "그렇/VA+구나/EC"
          },
          {
            "id": 9,
            "text": "1 : 왜 외가는 안 가?",
            "norm_text": "왜 외가는 안 가?",
            "speaker": {
              "id": "1번",
              "sex": "여성",
              "age": "20대"
            },
            "speechAct": "(지시) 질문하기",
            "morpheme": "왜/MAG+외가/NNG+는/JX+안/MAG+가/VV+EF"
          },
          {
            "id": 10,
            "text": "2 : 멀어 가지고 아빠가 안 가더라고 키키",
            "norm_text": "멀어 가지고 아빠가 안 가더라고 키키",
            "speaker": {
              "id": "2번",
              "sex": "남성",
              "age": "20대"
            },
            "speechAct": "(단언) 주장하기",
            "morpheme": "멀/VA+어/EC+가지/VX+고/EC+아빠/NNG+가/JKS+안/MAG+가/VV+더라고/EC+키/NNG+키/XSV+ETN"
          },
          {
            "id": 11,
            "text": "2 : 너무하지?",
            "norm_text": "너무하지?",
            "speaker": {
              "id": "2번",
              "sex": "남성",
              "age": "20대"
            },
            "speechAct": "(지시) 질문하기",
            "morpheme": "너무/MAG+하/VV+지/EF"
          },
          {
            "id": 12,
            "text": "1 : 헐 대박 외가집 지역이 어디인데?",
            "norm_text": "헐 대박 외가집 지역이 어디인데?",
            "speaker": {
              "id": "1번",
              "sex": "여성",
              "age": "20대"
            },
            "speechAct": "(지시) 질문하기",
            "morpheme": "헐/VV+JKO+대/XPN+박외/NNG+가/JKS+집/NNG+지역/NNG+이/JKS+어디/NP+인데/VCP+EF"
          },
          {
            "id": 13,
            "text": "2 : 경기도 양평 키키 명절에 가기엔 좀 무리야",
            "norm_text": "경기도 양평 키키 명절에 가기엔 좀 무리야",
            "speaker": {
              "id": "2번",
              "sex": "남성",
              "age": "20대"
            },
            "speechAct": "(단언) 주장하기",
            "morpheme": "경기도/NNP+양평/NNG+키/NNG+키/NNG+명절/NNG+에/JKB+가/VV+기/ETN+엔/JKB+JX+좀/MAG+무리/NNG+야/VCP+EF"
          },
          {
            "id": 14,
            "text": "1 : 아 양평 키키 양평은 진짜 마음먹고 가야겠다!",
            "norm_text": "아 양평 키키 양평은 진짜 마음먹고 가야겠다!",
            "speaker": {
              "id": "1번",
              "sex": "여성",
              "age": "20대"
            },
            "speechAct": "(단언) 주장하기",
            "morpheme": "아/IC+양평/NNG+키/NNG+키/NNG+양평/NNG+은/JX+진짜/MAG+마음먹/VV+고/EC+가/VX+야겠다/EC+VX+EP+EF"
          },
          {
            "id": 15,
            "text": "2 : 어 근데 안 가주니까 엄마가 우울해 하지 키키",
            "norm_text": "어 근데 안 가주니까 엄마가 우울해 하지 키키",
            "speaker": {
              "id": "2번",
              "sex": "남성",
              "age": "20대"
            },
            "speechAct": "(단언) 주장하기",
            "morpheme": "어/IC+근데/MAJ+안/MAG+가/VV+EC+주/VX+니까/EC+엄마/NNG+가/JKS+우울/NNG+해/XSV+EC+하/VV+지/EC+키/NNG+키/XSV+ETN"
          },
          {
            "id": 16,
            "text": "1 : 그니까 오빠가 어무니 모시고 가!",
            "norm_text": "그니까 오빠가 어무니 모시고 가!",
            "speaker": {
              "id": "1번",
              "sex": "여성",
              "age": "20대"
            },
            "speechAct": "(단언) 주장하기",
            "morpheme": "그니까/MAJ+오빠/NNG+가/JKS+어/IC+무니/NNG+모시/VV+고/EC+가/VX+EF"
          },
          {
            "id": 17,
            "text": "2 : 그러고 싶은데 불효자는 웁니다 키키",
            "norm_text": "그러고 싶은데 불효자는 웁니다 키키",
            "speaker": {
              "id": "2번",
              "sex": "남성",
              "age": "20대"
            },
            "speechAct": "(단언) 주장하기",
            "morpheme": "그러/VV+고/EC+싶/VX+은데/EC+불효자/NNG+는/JX+웁/VA+니/EC+다키키/NNP"
          },
          {
            "id": 18,
            "text": "1 : 키키 할 ㅜㅜ 그래도 더 늦기 전에 내년 설에는 가 봐!",
            "norm_text": "키키 할 ㅜㅜ 그래도 더 늦기 전에 내년 설에는 가 봐!",
            "speaker": {
              "id": "1번",
              "sex": "여성",
              "age": "20대"
            },
            "speechAct": "(지시) 충고/제안하기",
            "morpheme": "키/NNG+키/NNG+할/XSV+ETM+ㅜㅜ/UNKNOWN+그래도/VV+EC+더/MAG+늦/VA+기/ETN+전/NNG+에/JKB+내년/NNG+설/NNG+에/JKB+는/JX+가/VV+EC+봐/VX+EF"
          },
          {
            "id": 19,
            "text": "2 : 아니야",
            "norm_text": "아니야",
            "speaker": {
              "id": "2번",
              "sex": "남성",
              "age": "20대"
            },
            "speechAct": "(단언) 진술하기",
            "morpheme": "아니/VCN+야/EC"
          },
          {
            "id": 20,
            "text": "2 : 그냥 명절 말고 그전에 갔다 올게 키키",
            "norm_text": "그냥 명절 말고 그전에 갔다 올게 키키",
            "speaker": {
              "id": "2번",
              "sex": "남성",
              "age": "20대"
            },
            "speechAct": "(단언) 주장하기",
            "morpheme": "그냥/MAG+명절/NNG+말/VV+고/EC+그/MM+전/NNG+에/JKB+갔다올/VV+ETM+게/NNB+JKS+키/NNG+키/XSV+ETN"
          },
          {
            "id": 21,
            "text": "1 : 키키 오 좋은 생각이다",
            "norm_text": "키키 오 좋은 생각이다",
            "speaker": {
              "id": "1번",
              "sex": "여성",
              "age": "20대"
            },
            "speechAct": "(단언) 주장하기",
            "morpheme": "키/NNG+키/VV+오/EC+좋/VA+은/ETM+생각/NNG+이/VCP+다/EC"
          },
          {
            "id": 22,
            "text": "1 : 우리는 외가 어르신들 다 돌아가서 갈 고향이 없어,",
            "norm_text": "우리는 외가 어르신들 다 돌아가서 갈 고향이 없어,",
            "speaker": {
              "id": "1번",
              "sex": "여성",
              "age": "20대"
            },
            "speechAct": "(단언) 진술하기",
            "morpheme": "우리/NP+는/JX+외가/NNG+어르신/NNG+들/XSN+다/MAG+돌아가/VV+서/EC+갈/VX+ETM+고향/NNG+이/JKS+없/VA+어/EF+,/SC"
          },
          {
            "id": 23,
            "text": "2 : 아 엄마가 그럼 명절에 외로워 하시겠네 ㅠㅠ",
            "norm_text": "아 엄마가 그럼 명절에 외로워 하시겠네 ㅠㅠ",
            "speaker": {
              "id": "2번",
              "sex": "남성",
              "age": "20대"
            },
            "speechAct": "(단언) 주장하기",
            "morpheme": "아/IC+엄마/NNG+가/JKS+그럼/MAJ+명절/NNG+에/JKB+외로워/VA+EC+하/VX+시/EP+겠/EP+네/EF+ㅠㅠ/UNKNOWN"
          }
        ]
      }
    }
  ]
}