{
  "dataset": {
    "identifier": 101809,
    "name": "KAKAO_1632_10_set",
    "src_path": "/data/file/cubeManager/PROJECT001/77/txt202110291511560831103/KAKAO_1632_10_set/",
    "label_path": "/data/file/cubeManager/PROJECT001/77/txt202110291511560831103/KAKAO_1632_10_set/",
    "category": 2,
    "type": 0
  },
  "licenses": {
    "name": "Apache License 1.0",
    "url": "http://www.apache.org/licenses/LICENSE-1.0"
  },
  "info": [
    {
      "id": 109772,
      "filename": "KAKAO_1632_10.txt",
      "title": "KAKAO_1632_10",
      "mediatype": "SNS",
      "medianame": "카카오톡",
      "category": "일상대화",
      "date": "2021-10-29",
      "size": 566,
      "annotations": {
        "subject": "스포츠/레저",
        "speaker_type": "1:1",
        "size": 566,
        "word_size": 197,
        "text": "1 : 야외활동은 즐겨 하는 편이야? 키키\n2 : 넵 하하 집에 있는 것보다 돌아다니는걸 더 좋아해요\n1 : 키키 오 키키 뭐하는 거 좋아해? 키키\n1 : 자전거 좋아함?\n2 : 넵 하하 창원에 누비자 알아요? 그거 자주 타고 다녀요\n1 : 키키 누비자?\n1 : 몰라 그것도 뭐 자전거 무료 대여?\n2 : 넵 하하 서울에 따릉이처럼 무료 대여는 아니고 돈 내고 대여하는 거에요 하하\n1 : 오 키키 그렇구만 키키\n1 : 우리 아빠는 자전거 타고 시장 간다고 나감\n2 : 오 자전거 잘 타고 다니시네요 하하 건강에 좋죠\n1 : 옹 키키 밑에 층에서 주셔서 잘 타고 다니심\n2 : 오 득템했네요 하하\n2 : 자전거 있으면 또 타고 다니죠 하하\n1 : 옹 키키 득템해서 홍삼 한 박스 갖다 드림 키키\n2 : 키키 좋네요 하하\n2 : 누나는 자전거 잘 타요?\n1 : 나는 앞에 사람 없으면 잘 탐 키키\n2 : 아 하하 진로 변경이 좀 어렵나봐요\n1 : 키키 앞에 사람 있으면 긴장 돼서 키키\n2 : 아하 자전거도 타다 보면 괜찮아져요 하하\n1 : 키키 옹 뭐 가끔 타서 키키\n2 : 맞아요 하하\n2 : 날씨 좋을 때 타면 기분 좋아요\n2 : 언제 한번 같이 타요",
        "lines": [
          {
            "id": 1,
            "text": "1 : 야외활동은 즐겨 하는 편이야? 키키",
            "norm_text": "야외활동은 즐겨 하는 편이야? 키키",
            "speaker": {
              "id": "1번",
              "sex": "여성",
              "age": "20대"
            },
            "speechAct": "(지시) 질문하기",
            "morpheme": "야외/NNG+활동/NNG+은/JX+즐겨/VV+EC+하/VV+는/ETM+편/NNB+이/VCP+야/EF+키/NNG+키/XSV+ETN"
          },
          {
            "id": 2,
            "text": "2 : 넵 하하 집에 있는 것보다 돌아다니는걸 더 좋아해요",
            "norm_text": "넵 하하 집에 있는 것보다 돌아다니는걸 더 좋아해요",
            "speaker": {
              "id": "2번",
              "sex": "남성",
              "age": "20대"
            },
            "speechAct": "(단언) 주장하기",
            "morpheme": "넵/NNG+하하/MAG+집/NNG+에/JKB+있/VV+는/ETM+것/NNB+보다/JKB+돌아다니/VV+는/ETM+걸/NNB+JKO+더/MAG+좋/VA+아/EC+해요/VX+EC"
          },
          {
            "id": 3,
            "text": "1 : 키키 오 키키 뭐하는 거 좋아해? 키키",
            "norm_text": "키키 오 키키 뭐하는 거 좋아해? 키키",
            "speaker": {
              "id": "1번",
              "sex": "여성",
              "age": "20대"
            },
            "speechAct": "(지시) 질문하기",
            "morpheme": "키키/NNP+오키/NNP+키/NNG+뭐/IC+하/VV+는/ETM+거/NNB+좋/VA+아/EC+해/VX+EF+키/NNG+키/XSV+ETN"
          },
          {
            "id": 4,
            "text": "1 : 자전거 좋아함?",
            "norm_text": "자전거 좋아함?",
            "speaker": {
              "id": "1번",
              "sex": "여성",
              "age": "20대"
            },
            "speechAct": "(지시) 질문하기",
            "morpheme": "자전거/NNG+좋/VA+아함/IC+ETN"
          },
          {
            "id": 5,
            "text": "2 : 넵 하하 창원에 누비자 알아요? 그거 자주 타고 다녀요",
            "norm_text": "넵 하하 창원에 누비자 알아요? 그거 자주 타고 다녀요",
            "speaker": {
              "id": "2번",
              "sex": "남성",
              "age": "20대"
            },
            "speechAct": "(지시) 질문하기",
            "morpheme": "넵/NNG+하/XSV+하창원/NNP+에/JKB+누비/VV+자/EC+알/VV+아요/EF+그거/NP+자주/MAG+타/VV+고/EC+다녀요/VV+EF"
          },
          {
            "id": 6,
            "text": "1 : 키키 누비자?",
            "norm_text": "키키 누비자?",
            "speaker": {
              "id": "1번",
              "sex": "여성",
              "age": "20대"
            },
            "speechAct": "(지시) 질문하기",
            "morpheme": "키/NNG+키/XSV+ETN+누비/VV+자/EF"
          },
          {
            "id": 7,
            "text": "1 : 몰라 그것도 뭐 자전거 무료 대여?",
            "norm_text": "몰라 그것도 뭐 자전거 무료 대여?",
            "speaker": {
              "id": "1번",
              "sex": "여성",
              "age": "20대"
            },
            "speechAct": "(단언) 진술하기",
            "morpheme": "몰라/VV+EF+그것/NP+도/JX+뭐/IC+자전거/NNG+무료/NNG+대여/NNG"
          },
          {
            "id": 8,
            "text": "2 : 넵 하하 서울에 따릉이처럼 무료 대여는 아니고 돈 내고 대여하는 거에요 하하",
            "norm_text": "넵 하하 서울에 따릉이처럼 무료 대여는 아니고 돈 내고 대여하는 거에요 하하",
            "speaker": {
              "id": "2번",
              "sex": "남성",
              "age": "20대"
            },
            "speechAct": "(단언) 주장하기",
            "morpheme": "넵/NNG+하하/MAG+서울/NNP+에/JKB+따/VV+EC+릉/NNG+이/VCP+처럼/JKB+무료/NNG+대여/NNG+는/JX+아니/VCN+고/EC+돈/NNG+내/VV+고/EC+대여/NNG+하/XSV+는/ETM+거/NNB+에/JKB+요하/NNG+하/XSV"
          },
          {
            "id": 9,
            "text": "1 : 오 키키 그렇구만 키키",
            "norm_text": "오 키키 그렇구만 키키",
            "speaker": {
              "id": "1번",
              "sex": "여성",
              "age": "20대"
            },
            "speechAct": "(단언) 진술하기",
            "morpheme": "오키/NNP+키/NNG+그렇/VA+구/EC+만/JX+키/NNG+키/XSV+ETN"
          },
          {
            "id": 10,
            "text": "1 : 우리 아빠는 자전거 타고 시장 간다고 나감",
            "norm_text": "우리 아빠는 자전거 타고 시장 간다고 나감",
            "speaker": {
              "id": "1번",
              "sex": "여성",
              "age": "20대"
            },
            "speechAct": "(단언) 진술하기",
            "morpheme": "우리/NP+아빠/NNG+는/JX+자전거/NNG+타/VV+고/EC+시장/NNG+간다고/VV+EC+나감/VX+ETN"
          },
          {
            "id": 11,
            "text": "2 : 오 자전거 잘 타고 다니시네요 하하 건강에 좋죠",
            "norm_text": "오 자전거 잘 타고 다니시네요 하하 건강에 좋죠",
            "speaker": {
              "id": "2번",
              "sex": "남성",
              "age": "20대"
            },
            "speechAct": "(단언) 진술하기",
            "morpheme": "오/NR+자전거/NNG+잘/MAG+타/VV+고/EC+다니/VV+시/EP+네요/EF+하하/MAG+건강/NNG+에/JKB+좋/VA+죠/EF"
          },
          {
            "id": 12,
            "text": "1 : 옹 키키 밑에 층에서 주셔서 잘 타고 다니심",
            "norm_text": "옹 키키 밑에 층에서 주셔서 잘 타고 다니심",
            "speaker": {
              "id": "1번",
              "sex": "여성",
              "age": "20대"
            },
            "speechAct": "(단언) 진술하기",
            "morpheme": "옹/NNG+키/NNG+키/NNG+밑/NNG+에/JKB+층/NNG+에서/JKB+주/VV+셔서/EP+EC+잘/MAG+타/VV+고/EC+다니/VV+심/EP+ETN"
          },
          {
            "id": 13,
            "text": "2 : 오 득템했네요 하하",
            "norm_text": "오 득템했네요 하하",
            "speaker": {
              "id": "2번",
              "sex": "남성",
              "age": "20대"
            },
            "speechAct": "(단언) 진술하기",
            "morpheme": "오/NR+득템/NNG+했/XSV+EP+네요/EF+하하/MAG"
          },
          {
            "id": 14,
            "text": "2 : 자전거 있으면 또 타고 다니죠 하하",
            "norm_text": "자전거 있으면 또 타고 다니죠 하하",
            "speaker": {
              "id": "2번",
              "sex": "남성",
              "age": "20대"
            },
            "speechAct": "(단언) 진술하기",
            "morpheme": "자전거/NNG+있/VV+으면/EC+또/MAG+타/VV+고/EC+다니/VV+죠/EF+하하/MAG"
          },
          {
            "id": 15,
            "text": "1 : 옹 키키 득템해서 홍삼 한 박스 갖다 드림 키키",
            "norm_text": "옹 키키 득템해서 홍삼 한 박스 갖다 드림 키키",
            "speaker": {
              "id": "1번",
              "sex": "여성",
              "age": "20대"
            },
            "speechAct": "(단언) 진술하기",
            "morpheme": "옹/NNG+키/NNG+키/NNG+득템/NNG+해서/XSV+EC+홍삼/NNG+한/XSA+ETM+박스/NNG+갖/VV+다/EC+드림/VV+ETM+키/NNG+키/XSV+ETN"
          },
          {
            "id": 16,
            "text": "2 : 키키 좋네요 하하",
            "norm_text": "키키 좋네요 하하",
            "speaker": {
              "id": "2번",
              "sex": "남성",
              "age": "20대"
            },
            "speechAct": "(단언) 진술하기",
            "morpheme": "키/NNG+키/XSV+ETN+좋/VA+네요/EF+하하/MAG"
          },
          {
            "id": 17,
            "text": "2 : 누나는 자전거 잘 타요?",
            "norm_text": "누나는 자전거 잘 타요?",
            "speaker": {
              "id": "2번",
              "sex": "남성",
              "age": "20대"
            },
            "speechAct": "(지시) 질문하기",
            "morpheme": "누나/NNG+는/JX+자전거/NNG+잘/MAG+타/VV+요/EF"
          },
          {
            "id": 18,
            "text": "1 : 나는 앞에 사람 없으면 잘 탐 키키",
            "norm_text": "나는 앞에 사람 없으면 잘 탐 키키",
            "speaker": {
              "id": "1번",
              "sex": "여성",
              "age": "20대"
            },
            "speechAct": "(단언) 주장하기",
            "morpheme": "나/NP+는/JX+앞/NNG+에/JKB+사람/NNG+없/VA+으면/EC+잘/MAG+탐/NNG+키/NNG+키/XSV+ETN"
          },
          {
            "id": 19,
            "text": "2 : 아 하하 진로 변경이 좀 어렵나봐요",
            "norm_text": "아 하하 진로 변경이 좀 어렵나봐요",
            "speaker": {
              "id": "2번",
              "sex": "남성",
              "age": "20대"
            },
            "speechAct": "(단언) 진술하기",
            "morpheme": "아하하/MAG+진로/NNG+변경/NNG+이/JKS+좀/MAG+어렵/VA+나/EC+봐요/VX+EC"
          },
          {
            "id": 20,
            "text": "1 : 키키 앞에 사람 있으면 긴장 돼서 키키",
            "norm_text": "키키 앞에 사람 있으면 긴장 돼서 키키",
            "speaker": {
              "id": "1번",
              "sex": "여성",
              "age": "20대"
            },
            "speechAct": "(단언) 주장하기",
            "morpheme": "키/NNG+키/NNG+앞/NNG+에/JKB+사람/NNG+있/VV+으면/EC+긴장/NNG+돼서/XSV+EC+키/NNG+키/XSV+ETN"
          },
          {
            "id": 21,
            "text": "2 : 아하 자전거도 타다 보면 괜찮아져요 하하",
            "norm_text": "아하 자전거도 타다 보면 괜찮아져요 하하",
            "speaker": {
              "id": "2번",
              "sex": "남성",
              "age": "20대"
            },
            "speechAct": "(단언) 진술하기",
            "morpheme": "아하/IC+자전거/NNG+도/JX+타/VV+다/EC+보/VX+면/EC+괜찮/VA+아/EC+져요/VX+EF+하하/MAG"
          },
          {
            "id": 22,
            "text": "1 : 키키 옹 뭐 가끔 타서 키키",
            "norm_text": "키키 옹 뭐 가끔 타서 키키",
            "speaker": {
              "id": "1번",
              "sex": "여성",
              "age": "20대"
            },
            "speechAct": "(단언) 진술하기",
            "morpheme": "키/NNG+키/XSV+ETN+옹/NNB+뭐/IC+가끔/MAG+타/VV+서/EC+키/NNG+키/XSV+ETN"
          },
          {
            "id": 23,
            "text": "2 : 맞아요 하하",
            "norm_text": "맞아요 하하",
            "speaker": {
              "id": "2번",
              "sex": "남성",
              "age": "20대"
            },
            "speechAct": "(단언) 주장하기",
            "morpheme": "맞/VV+아요/EF+하하/MAG"
          },
          {
            "id": 24,
            "text": "2 : 날씨 좋을 때 타면 기분 좋아요",
            "norm_text": "날씨 좋을 때 타면 기분 좋아요",
            "speaker": {
              "id": "2번",
              "sex": "남성",
              "age": "20대"
            },
            "speechAct": "(단언) 진술하기",
            "morpheme": "날씨/NNG+좋/VA+을/ETM+때/NNG+타/VV+면/EC+기분/NNG+좋/VA+아요/EC"
          },
          {
            "id": 25,
            "text": "2 : 언제 한번 같이 타요",
            "norm_text": "언제 한번 같이 타요",
            "speaker": {
              "id": "2번",
              "sex": "남성",
              "age": "20대"
            },
            "speechAct": "(지시) 충고/제안하기",
            "morpheme": "언제/MAG+한/MM+번/NNBC+같이/MAG+타/VV+요/EC"
          }
        ]
      }
    }
  ]
}