{
  "dataset": {
    "identifier": 135231,
    "name": "KAKAO_4381_05",
    "src_path": "/data/file/cubeManager/PROJECT001/68/txt20211105095244065576/KAKAO_4381_05/",
    "label_path": "/data/file/cubeManager/PROJECT001/68/txt20211105095244065576/KAKAO_4381_05/",
    "category": 2,
    "type": 0
  },
  "licenses": {
    "name": "Apache License 1.0",
    "url": "http://www.apache.org/licenses/LICENSE-1.0"
  },
  "info": [
    {
      "id": 138223,
      "filename": "KAKAO_4381_05.txt",
      "title": "KAKAO_4381_05",
      "mediatype": "SNS",
      "medianame": "카카오톡",
      "category": "일상대화",
      "date": "2021-11-05",
      "size": 233,
      "annotations": {
        "subject": "군대",
        "speaker_type": "다자간 대화",
        "size": 233,
        "word_size": 76,
        "text": "1 : **가 군인한테 뿅 반한듯\n2 : 응 군인? 어디서 봤어?\n3 : 아까 군인옷 멋지다고 하더니\n1 : 응 맞아 아까 군인들 봤었거든\n2 : 군인이 왜 어디서 ?\n3 : 아까 단국대에서 ROTC 행사 했나봐\n1 : 응 그거때문에 군인들 많이 본듯\n2 : RT가 대학교에서 뭘 하나?\n3 : 그러게요 뭔가 웅장하긴 하던데\n1 : 군인들이 그런 행사들 엄청 좋아해서 그래\n2 : 그래도 학교에서 이시국에?\n3 : 맞아 사람들 말 많을듯",
        "lines": [
          {
            "id": 1,
            "text": "1 : **가 군인한테 뿅 반한듯",
            "norm_text": "**가 군인한테 뿅 반한듯",
            "speaker": {
              "id": "1번",
              "sex": "남성",
              "age": "40대"
            },
            "speechAct": "(단언) 진술하기",
            "morpheme": "*/SY+*/SY+가/JKS+군인/NNG+한테/JKB+뿅/MAG+반한/VV+ETM+듯/NNB"
          },
          {
            "id": 2,
            "text": "2 : 응 군인? 어디서 봤어?",
            "norm_text": "응 군인? 어디서 봤어?",
            "speaker": {
              "id": "2번",
              "sex": "여성",
              "age": "30대"
            },
            "speechAct": "(지시) 질문하기",
            "morpheme": "응/IC+군인/NNG+어디/NP+서/JKB+봤/VV+EP+어/EF"
          },
          {
            "id": 3,
            "text": "3 : 아까 군인옷 멋지다고 하더니",
            "norm_text": "아까 군인옷 멋지다고 하더니",
            "speaker": {
              "id": "3번",
              "sex": "여성",
              "age": "30대"
            },
            "speechAct": "(단언) 진술하기",
            "morpheme": "아까/MAG+군인/NNG+옷/NNG+멋지/VA+다고/EC+하/VV+더니/EC"
          },
          {
            "id": 4,
            "text": "1 : 응 맞아 아까 군인들 봤었거든",
            "norm_text": "응 맞아 아까 군인들 봤었거든",
            "speaker": {
              "id": "1번",
              "sex": "남성",
              "age": "40대"
            },
            "speechAct": "(단언) 진술하기",
            "morpheme": "응/IC+맞아/IC+아까/MAG+군인/NNG+들/XSN+봤었/VV+EP+거든/EC"
          },
          {
            "id": 5,
            "text": "2 : 군인이 왜 어디서 ?",
            "norm_text": "군인이 왜 어디서 ?",
            "speaker": {
              "id": "2번",
              "sex": "여성",
              "age": "30대"
            },
            "speechAct": "(지시) 질문하기",
            "morpheme": "군인/NNG+이/JKS+왜/MAG+어디/NP+서/JKB"
          },
          {
            "id": 6,
            "text": "3 : 아까 단국대에서 ROTC 행사 했나봐",
            "norm_text": "아까 단국대에서 ROTC 행사 했나봐",
            "speaker": {
              "id": "3번",
              "sex": "여성",
              "age": "30대"
            },
            "speechAct": "(단언) 진술하기",
            "morpheme": "아까/MAG+단국/NNG+대/XSN+에서/JKB+ROTC/SL+행사/NNG+했/XSV+EP+나/EC+봐/VX+EC"
          },
          {
            "id": 7,
            "text": "1 : 응 그거때문에 군인들 많이 본듯",
            "norm_text": "응 그거때문에 군인들 많이 본듯",
            "speaker": {
              "id": "1번",
              "sex": "남성",
              "age": "40대"
            },
            "speechAct": "(단언) 진술하기",
            "morpheme": "응/IC+그거/NP+때문/NNB+에/JKB+군인/NNG+들/XSN+많이/MAG+본/VV+ETM+듯/NNB"
          },
          {
            "id": 8,
            "text": "2 : RT가 대학교에서 뭘 하나?",
            "norm_text": "RT가 대학교에서 뭘 하나?",
            "speaker": {
              "id": "2번",
              "sex": "여성",
              "age": "30대"
            },
            "speechAct": "(지시) 질문하기",
            "morpheme": "RT/SL+가/JKS+대학교/NNG+에서/JKB+뭘/NP+JKO+하나/NR"
          },
          {
            "id": 9,
            "text": "3 : 그러게요 뭔가 웅장하긴 하던데",
            "norm_text": "그러게요 뭔가 웅장하긴 하던데",
            "speaker": {
              "id": "3번",
              "sex": "여성",
              "age": "30대"
            },
            "speechAct": "(단언) 진술하기",
            "morpheme": "그러게/IC+요/JX+뭔가/NP+VCP+EC+웅장/XR+하/XSA+긴/ETN+JX+하/VX+던데/EC"
          },
          {
            "id": 10,
            "text": "1 : 군인들이 그런 행사들 엄청 좋아해서 그래",
            "norm_text": "군인들이 그런 행사들 엄청 좋아해서 그래",
            "speaker": {
              "id": "1번",
              "sex": "남성",
              "age": "40대"
            },
            "speechAct": "(단언) 진술하기",
            "morpheme": "군인/NNG+들/XSN+이/JKS+그런/MM+행사/NNG+들/XSN+엄청/MAG+좋/VA+아/EC+해서/VV+EC+그래/VV+EC"
          },
          {
            "id": 11,
            "text": "2 : 그래도 학교에서 이시국에?",
            "norm_text": "그래도 학교에서 이시국에?",
            "speaker": {
              "id": "2번",
              "sex": "여성",
              "age": "30대"
            },
            "speechAct": "(지시) 질문하기",
            "morpheme": "그래도/MAJ+학교/NNG+에서/JKB+이/MM+시국/NNG+에/JKB"
          },
          {
            "id": 12,
            "text": "3 : 맞아 사람들 말 많을듯",
            "norm_text": "맞아 사람들 말 많을듯",
            "speaker": {
              "id": "3번",
              "sex": "여성",
              "age": "30대"
            },
            "speechAct": "(단언) 진술하기",
            "morpheme": "맞/VV+아/EC+사람/NNG+들/XSN+말/NNG+많/VA+을/ETM+듯/NNB"
          }
        ]
      }
    }
  ]
}