{
  "dataset": {
    "identifier": 36769,
    "name": "KAKAO_3258_12_set",
    "src_path": "/data/file/cubeManager/PROJECT001/47/txt20211006135223070940/KAKAO_3258_12_set/",
    "label_path": "/data/file/cubeManager/PROJECT001/47/txt20211006135223070940/KAKAO_3258_12_set/",
    "category": 2,
    "type": 0
  },
  "licenses": {
    "name": "Apache License 1.0",
    "url": "http://www.apache.org/licenses/LICENSE-1.0"
  },
  "info": [
    {
      "id": 44418,
      "filename": "KAKAO_3258_12.txt",
      "title": "KAKAO_3258_12",
      "mediatype": "SNS",
      "medianame": "카카오톡",
      "category": "일상대화",
      "date": "2021-10-06",
      "size": 277,
      "annotations": {
        "subject": "여행",
        "speaker_type": "1:1",
        "size": 277,
        "word_size": 90,
        "text": "1 : 뉴욕 여행 가고 싶어 ㅠㅠ\n2 : 뉴욕은 너무 도시적이지 않아?\n1 : 그 도시적인 화려함을 느끼러 가는거지 하하\n2 : 난 차라리 보스턴이 나은것 같아\n1 : 오 그 이유는 뭐라고 생각해?\n2 : 보스턴은 약간 중후한 매력? 을 느낄 수 있잖아\n1 : 맞아 하하 둘다 매력이 있지\n2 : 사실 미국 여행가면 두곳을 다 같이 가야지\n1 : 맞아 가까이에 있으니까 다 둘러보고 와야해 하하\n2 : 보스턴 가면 하버드 다녀와야지\n1 : 맞아 키키 다니진 못해도 구경은 해야지\n2 : 보스턴 가면 하버드 다녀와야지",
        "lines": [
          {
            "id": 1,
            "text": "1 : 뉴욕 여행 가고 싶어 ㅠㅠ",
            "norm_text": "뉴욕 여행 가고 싶어 ㅠㅠ",
            "speaker": {
              "id": "1번",
              "sex": "여성",
              "age": "20대"
            },
            "speechAct": "(단언) 주장하기",
            "morpheme": "뉴욕/NNP+여행/NNG+가/VV+고/EC+싶/VX+어/EC+ㅠㅠ/UNKNOWN"
          },
          {
            "id": 2,
            "text": "2 : 뉴욕은 너무 도시적이지 않아?",
            "norm_text": "뉴욕은 너무 도시적이지 않아?",
            "speaker": {
              "id": "2번",
              "sex": "남성",
              "age": "20대"
            },
            "speechAct": "(지시) 질문하기",
            "morpheme": "뉴욕/NNP+은/JX+너무/MAG+도시/NNG+적/XSN+이/VCP+지/EC+않/VX+아/EF"
          },
          {
            "id": 3,
            "text": "1 : 그 도시적인 화려함을 느끼러 가는거지 하하",
            "norm_text": "그 도시적인 화려함을 느끼러 가는거지 하하",
            "speaker": {
              "id": "1번",
              "sex": "여성",
              "age": "20대"
            },
            "speechAct": "(단언) 주장하기",
            "morpheme": "그/MM+도시/NNG+적/XSN+인/VCP+ETM+화려/XR+함/XSA+ETN+을/JKO+느끼/VV+러/EC+가/VX+는/ETM+거/NNB+지하/NNG+하/XSV"
          },
          {
            "id": 4,
            "text": "2 : 난 차라리 보스턴이 나은것 같아",
            "norm_text": "난 차라리 보스턴이 나은것 같아",
            "speaker": {
              "id": "2번",
              "sex": "남성",
              "age": "20대"
            },
            "speechAct": "(단언) 주장하기",
            "morpheme": "난/NP+JX+차라리/MAG+보스턴/NNG+이/JKS+나/VA+은/ETM+것/NNB+같/VA+아/EC"
          },
          {
            "id": 5,
            "text": "1 : 오 그 이유는 뭐라고 생각해?",
            "norm_text": "오 그 이유는 뭐라고 생각해?",
            "speaker": {
              "id": "1번",
              "sex": "여성",
              "age": "20대"
            },
            "speechAct": "(지시) 질문하기",
            "morpheme": "오/IC+그/MM+이유/NNG+는/JX+뭐/NP+라고/VCP+EC+생각/NNG+해/XSV+EF"
          },
          {
            "id": 6,
            "text": "2 : 보스턴은 약간 중후한 매력? 을 느낄 수 있잖아",
            "norm_text": "보스턴은 약간 중후한 매력? 을 느낄 수 있잖아",
            "speaker": {
              "id": "2번",
              "sex": "남성",
              "age": "20대"
            },
            "speechAct": "(단언) 주장하기",
            "morpheme": "보스턴/NNG+은/JX+약간/MAG+중후/XR+한/XSA+ETM+매력/NNG+?/SY+을/JKO+느낄/VV+ETM+수/NNB+있/VV+잖아/EC"
          },
          {
            "id": 7,
            "text": "1 : 맞아 하하 둘다 매력이 있지",
            "norm_text": "맞아 하하 둘다 매력이 있지",
            "speaker": {
              "id": "1번",
              "sex": "여성",
              "age": "20대"
            },
            "speechAct": "(단언) 주장하기",
            "morpheme": "맞/VV+아/EC+하하/MAG+둘/NR+다/MAG+매력/NNG+이/JKS+있/VV+지/EC"
          },
          {
            "id": 8,
            "text": "2 : 사실 미국 여행가면 두곳을 다 같이 가야지",
            "norm_text": "사실 미국 여행가면 두곳을 다 같이 가야지",
            "speaker": {
              "id": "2번",
              "sex": "남성",
              "age": "20대"
            },
            "speechAct": "(단언) 주장하기",
            "morpheme": "사실/MAG+미국/NNP+여행/NNG+가/VV+면/EC+두/MM+곳/NNG+을/JKO+다/MAG+같이/MAG+가/VV+야지/EC"
          },
          {
            "id": 9,
            "text": "1 : 맞아 가까이에 있으니까 다 둘러보고 와야해 하하",
            "norm_text": "맞아 가까이에 있으니까 다 둘러보고 와야해 하하",
            "speaker": {
              "id": "1번",
              "sex": "여성",
              "age": "20대"
            },
            "speechAct": "(단언) 주장하기",
            "morpheme": "맞/VV+아/EC+가까이/NNG+에/JKB+있/VV+으니까/EC+다/MAG+둘러보/VV+고/EC+와야/VV+EC+해하/NNG+하/XSV"
          },
          {
            "id": 10,
            "text": "2 : 보스턴 가면 하버드 다녀와야지",
            "norm_text": "보스턴 가면 하버드 다녀와야지",
            "speaker": {
              "id": "2번",
              "sex": "남성",
              "age": "20대"
            },
            "speechAct": "(지시) 충고/제안하기",
            "morpheme": "보스턴/NNG+가/VV+면/EC+하버드/NNP+다녀와야/VV+EC+VX+지/EC"
          },
          {
            "id": 11,
            "text": "1 : 맞아 키키 다니진 못해도 구경은 해야지",
            "norm_text": "맞아 키키 다니진 못해도 구경은 해야지",
            "speaker": {
              "id": "1번",
              "sex": "여성",
              "age": "20대"
            },
            "speechAct": "(단언) 주장하기",
            "morpheme": "맞아키키다니진못해도구경은해야지/UNKNOWN"
          },
          {
            "id": 12,
            "text": "2 : 보스턴 가면 하버드 다녀와야지",
            "norm_text": "보스턴 가면 하버드 다녀와야지",
            "speaker": {
              "id": "2번",
              "sex": "남성",
              "age": "20대"
            },
            "speechAct": "(단언) 주장하기",
            "morpheme": "보스턴/NNG+가/VV+면/EC+하버드/NNP+다녀와야/VV+EC+VX+지/EC"
          }
        ]
      }
    }
  ]
}