{
  "dataset": {
    "identifier": 154603,
    "name": "KAKAO_2236_06_set",
    "src_path": "/data/file/cubeManager/PROJECT001/86/txt20211116165531060213/KAKAO_2236_06_set/",
    "label_path": "/data/file/cubeManager/PROJECT001/86/txt20211116165531060213/KAKAO_2236_06_set/",
    "category": 2,
    "type": 0
  },
  "licenses": {
    "name": "Apache License 1.0",
    "url": "http://www.apache.org/licenses/LICENSE-1.0"
  },
  "info": [
    {
      "id": 169571,
      "filename": "KAKAO_2236_06.txt",
      "title": "KAKAO_2236_06",
      "mediatype": "SNS",
      "medianame": "카카오톡",
      "category": "일상대화",
      "date": "2021-11-16",
      "size": 248,
      "annotations": {
        "subject": "교육",
        "speaker_type": "1:1",
        "size": 248,
        "word_size": 88,
        "text": "1 : 매형 구몬 학습지 아시죠?\n2 : 응 키키 우리 어릴 때 많이 하던 거\n1 : 매형은 구몬 했어요?\n2 : 아니\n2 : 나는 눈높이 키키\n1 : 진짜 오랜만에 듣는다 키키\n2 : 눈높이 숫자 공부함\n1 : 저는 구몬 한자 했어요\n2 : 그때 인기 많아던 게 수학이랑 한자 ㅋ\n1 : 네 지금은 한자보다는 영어를 많이 하죠\n2 : 그때는 학습지 선생님들이 집으로 왔잖아\n1 : 네 집에 와서 한 30분? 수업하고 갔죠~\n2 : 응 내 기억에도 짧게 한 것 같다",
        "lines": [
          {
            "id": 1,
            "text": "1 : 매형 구몬 학습지 아시죠?",
            "norm_text": "매형 구몬 학습지 아시죠?",
            "speaker": {
              "id": "1번",
              "sex": "남성",
              "age": "20대"
            },
            "speechAct": "(지시) 질문하기",
            "morpheme": "매형/NNG+구몬/NNP+학습/NNG+지/VV+아시/EP+죠/EF"
          },
          {
            "id": 2,
            "text": "2 : 응 키키 우리 어릴 때 많이 하던 거",
            "norm_text": "응 키키 우리 어릴 때 많이 하던 거",
            "speaker": {
              "id": "2번",
              "sex": "남성",
              "age": "40대"
            },
            "speechAct": "(단언) 주장하기",
            "morpheme": "응/IC+키/NNG+키/XSV+ETN+우리/NP+어릴/VA+ETM+때/NNG+많이/MAG+하/VV+던/ETM+거/NNB"
          },
          {
            "id": 3,
            "text": "1 : 매형은 구몬 했어요?",
            "norm_text": "매형은 구몬 했어요?",
            "speaker": {
              "id": "1번",
              "sex": "남성",
              "age": "20대"
            },
            "speechAct": "(지시) 질문하기",
            "morpheme": "매형/NNG+은/JX+구몬/NNP+했/VV+EP+어요/EF"
          },
          {
            "id": 4,
            "text": "2 : 아니",
            "norm_text": "아니",
            "speaker": {
              "id": "2번",
              "sex": "남성",
              "age": "40대"
            },
            "speechAct": "(단언) 진술하기",
            "morpheme": "아니/IC"
          },
          {
            "id": 5,
            "text": "2 : 나는 눈높이 키키",
            "norm_text": "나는 눈높이 키키",
            "speaker": {
              "id": "2번",
              "sex": "남성",
              "age": "40대"
            },
            "speechAct": "(단언) 진술하기",
            "morpheme": "나/NP+는/JX+눈높이/NNG+키/NNG+키/XSV+ETN"
          },
          {
            "id": 6,
            "text": "1 : 진짜 오랜만에 듣는다 키키",
            "norm_text": "진짜 오랜만에 듣는다 키키",
            "speaker": {
              "id": "1번",
              "sex": "남성",
              "age": "20대"
            },
            "speechAct": "(단언) 주장하기",
            "morpheme": "진짜/MAG+오랜만/NNG+에/JKB+듣/VV+는/ETM+다키키/NNP"
          },
          {
            "id": 7,
            "text": "2 : 눈높이 숫자 공부함",
            "norm_text": "눈높이 숫자 공부함",
            "speaker": {
              "id": "2번",
              "sex": "남성",
              "age": "40대"
            },
            "speechAct": "(단언) 진술하기",
            "morpheme": "눈높이/NNG+숫자/NNG+공부/NNG+함/XSV+ETN"
          },
          {
            "id": 8,
            "text": "1 : 저는 구몬 한자 했어요",
            "norm_text": "저는 구몬 한자 했어요",
            "speaker": {
              "id": "1번",
              "sex": "남성",
              "age": "20대"
            },
            "speechAct": "N/A",
            "morpheme": "저/NP+는/JX+구몬/NNP+한자/NNG+했어요/XSV+EP+EC"
          },
          {
            "id": 9,
            "text": "2 : 그때 인기 많아던 게 수학이랑 한자 ㅋ",
            "norm_text": "그때 인기 많아던 게 수학이랑 한자 ㅋ",
            "speaker": {
              "id": "2번",
              "sex": "남성",
              "age": "40대"
            },
            "speechAct": "(단언) 진술하기",
            "morpheme": "그때인기많아던게수학이랑한자ㅋ/UNKNOWN"
          },
          {
            "id": 10,
            "text": "1 : 네 지금은 한자보다는 영어를 많이 하죠",
            "norm_text": "네 지금은 한자보다는 영어를 많이 하죠",
            "speaker": {
              "id": "1번",
              "sex": "남성",
              "age": "20대"
            },
            "speechAct": "(단언) 진술하기",
            "morpheme": "네/IC+지금/MAG+은/JX+한자/NNG+보다/JKB+는/JX+영어/NNG+를/JKO+많이/MAG+하/VV+죠/EC"
          },
          {
            "id": 11,
            "text": "2 : 그때는 학습지 선생님들이 집으로 왔잖아",
            "norm_text": "그때는 학습지 선생님들이 집으로 왔잖아",
            "speaker": {
              "id": "2번",
              "sex": "남성",
              "age": "40대"
            },
            "speechAct": "(단언) 진술하기",
            "morpheme": "그때/NNG+는/JX+학습지/NNG+선생/NNG+님/XSN+들/XSN+이/JKS+집/NNG+으로/JKB+왔/VV+EP+잖아/EC"
          },
          {
            "id": 12,
            "text": "1 : 네 집에 와서 한 30분? 수업하고 갔죠~",
            "norm_text": "네 집에 와서 한 30분? 수업하고 갔죠~",
            "speaker": {
              "id": "1번",
              "sex": "남성",
              "age": "20대"
            },
            "speechAct": "(단언) 진술하기",
            "morpheme": "네/IC+집/NNG+에/JKB+와서/VV+EC+한/VX+ETM+30/SN+분/NNBC+수업/NNG+하/XSV+고/EC+갔/VV+EP+죠/EF+~/SY"
          },
          {
            "id": 13,
            "text": "2 : 응 내 기억에도 짧게 한 것 같다",
            "norm_text": "응 내 기억에도 짧게 한 것 같다",
            "speaker": {
              "id": "2번",
              "sex": "남성",
              "age": "40대"
            },
            "speechAct": "(단언) 주장하기",
            "morpheme": "응/IC+내/NP+JKG+기억/NNG+에/JKB+도/JX+짧/VA+게/EC+한/VX+ETM+것/NNB+같/VA+다/EC"
          }
        ]
      }
    }
  ]
}