{
  "dataset": {
    "identifier": 41055,
    "name": "c2_20211012_0005_0107_01",
    "src_path": "/data/file/cubeManager/PROJECT018/41/txt20211008130955000811/c2_20211012_0005_0107_01/",
    "label_path": "/data/file/cubeManager/PROJECT018/41/txt20211008130955000811/c2_20211012_0005_0107_01/",
    "category": 2,
    "type": 0
  },
  "licenses": {
    "name": "Apache License 1.0",
    "url": "http://www.apache.org/licenses/LICENSE-1.0"
  },
  "info": [
    {
      "id": 53360,
      "filename": "c2_20210928_0020_0014_01.txt",
      "title": "c2_20210928_0020_0014_01",
      "mediatype": "SNS(게시판)",
      "medianame": "SNS(게시판)",
      "category": "목적대화",
      "date": "2021-10-08",
      "size": 334,
      "annotations": {
        "subject": "절차 문의",
        "speaker_type": "1:1",
        "size": 334,
        "word_size": 78,
        "text": "A.반갑습니다 상담사 #@이름#입니다\nB.중학교 재배정 관련해서 여쭤보고 싶은게 있는데요\nA.네 자세한 내용 말씀해 주시겠습니까\nB.중학교 입학 배정을 받고 타 시도로 이사를 가게 됐어요\nB.이런 경우에 재배정 받을 수 있나요\nA.타 시도 혹은 학교군 달리해서 거주지가 이전되었을 경우는요\nA.이월 삼일까지 거주지 이전된 학생은 재배정 받을 수 있습니다\nB.재배정 되는 학교는 선택 할 수 있나요\nA.거주지를 학구로 하는 초등학교 기준으로 추첨됩니다\nB.배정되면 연락이 오나요\nA.네 개별통보 드리구요 통보 받는 즉시 입학등록 절차 밟으시면 됩니다\nB.알겠습니다 그렇게 하겠습니다\nA.감사합니다 상담사 #@이름#였습니다",
        "lines": [
          {
            "id": 1,
            "text": "A.반갑습니다 상담사 #@이름#입니다",
            "norm_text": "A.반갑습니다 상담사 #@이름#입니다",
            "speaker": {
              "id": "A",
              "sex": "여성",
              "age": "2그룹(30대~40대)"
            },
            "speechAct": "인사하기",
            "morpheme": "A/SL+반갑/VA+습니다/EF+상담/NNG+사/NNG+#/SY+@/SY+이름/NNG+#/SY+입니다/VCP+EC"
          },
          {
            "id": 2,
            "text": "B.중학교 재배정 관련해서 여쭤보고 싶은게 있는데요",
            "norm_text": "B.중학교 재배정 관련해서 여쭤보고 싶은 게 있는데요",
            "speaker": {
              "id": "B",
              "sex": "여성",
              "age": "2그룹(30대~40대)"
            },
            "speechAct": "진술하기",
            "morpheme": "B/SL+./SY+중학교/NNG+재배정/NNG+관련/NNG+해서/XSV+EC+여쭤/VV+EC+보/VX+고/EC+싶/VX+은/ETM+게/NNB+JKS+있/VA+는데요/EC"
          },
          {
            "id": 3,
            "text": "A.네 자세한 내용 말씀해 주시겠습니까",
            "norm_text": "A.네 자세한 내용 말씀해 주시겠습니까",
            "speaker": {
              "id": "A",
              "sex": "여성",
              "age": "2그룹(30대~40대)"
            },
            "speechAct": "명령하기/요구하기",
            "morpheme": "A/SL+네/IC+자세/XR+한/XSA+ETM+내용/NNG+말씀/NNG+해/XSV+EC+주/VX+시/EP+겠/EP+습니까/EC"
          },
          {
            "id": 4,
            "text": "B.중학교 입학 배정을 받고 타 시도로 이사를 가게 됐어요",
            "norm_text": "B.중학교 입학 배정을 받고 타 시도로 이사를 가게 됐어요",
            "speaker": {
              "id": "B",
              "sex": "여성",
              "age": "2그룹(30대~40대)"
            },
            "speechAct": "진술하기",
            "morpheme": "B/SL+./SY+중학교/NNG+입학/NNG+배정/NNG+을/JKO+받/VV+고/EC+타/MM+시도/NNG+로/JKB+이사/NNG+를/JKO+가/VV+게/EC+됐/VV+EP+어요/EF"
          },
          {
            "id": 5,
            "text": "B.이런 경우에 재배정 받을 수 있나요",
            "norm_text": "B.이런 경우에 재배정 받을 수 있나요",
            "speaker": {
              "id": "B",
              "sex": "여성",
              "age": "2그룹(30대~40대)"
            },
            "speechAct": "명령하기/요구하기",
            "morpheme": "B/SL+이런/MM+경우/NNG+에/JKB+재배정/NNG+받/VV+을/ETM+수/NNB+있/VV+나요/EC"
          },
          {
            "id": 6,
            "text": "A.타 시도 혹은 학교군 달리해서 거주지가 이전되었을 경우는요",
            "norm_text": "A.타 시도 혹은 학교군 달리해서 거주지가 이전되었을 경우는요",
            "speaker": {
              "id": "A",
              "sex": "여성",
              "age": "2그룹(30대~40대)"
            },
            "speechAct": "진술하기",
            "morpheme": "A/SL+./SY+타시/NNG+도/JX+혹은/MAJ+학교/NNG+군/NNB+달리/MAG+해서/VV+EC+거주지/NNG+가/JKS+이전/NNG+되/XSV+었/EP+을/ETM+경우/NNG+는/JX+요/JX"
          },
          {
            "id": 7,
            "text": "A.이월 삼일까지 거주지 이전된 학생은 재배정 받을 수 있습니다",
            "norm_text": "A.이월 삼일까지 거주지 이전된 학생은 재배정 받을 수 있습니다",
            "speaker": {
              "id": "A",
              "sex": "여성",
              "age": "2그룹(30대~40대)"
            },
            "speechAct": "진술하기",
            "morpheme": "A/SL+./SY+이월/NNG+삼/NR+일/NNBC+까지/JX+거주지/NNG+이전/NNG+된/XSV+ETM+학생/NNG+은/JX+재배정/NNG+받/VV+을/ETM+수/NNB+있/VV+습니다/EF"
          },
          {
            "id": 8,
            "text": "B.재배정 되는 학교는 선택 할 수 있나요",
            "norm_text": "B.재배정 되는 학교는 선택 할 수 있나요",
            "speaker": {
              "id": "B",
              "sex": "여성",
              "age": "2그룹(30대~40대)"
            },
            "speechAct": "질문하기",
            "morpheme": "B/SL+./SY+재배정/NNG+되/XSV+는/ETM+학교/NNG+는/JX+선택/NNG+할/XSV+ETM+수/NNB+있/VV+나요/EC"
          },
          {
            "id": 9,
            "text": "A.거주지를 학구로 하는 초등학교 기준으로 추첨됩니다",
            "norm_text": "A.거주지를 학구로 하는 초등학교 기준으로 추첨됩니다",
            "speaker": {
              "id": "A",
              "sex": "여성",
              "age": "2그룹(30대~40대)"
            },
            "speechAct": "진술하기",
            "morpheme": "A/SL+./SY+거주지/NNG+를/JKO+학구/NNG+로/JKB+하/VV+는/ETM+초등/NNG+학교/NNG+기준/NNG+으로/JKB+추첨/NNG+됩니다/XSV+EC"
          },
          {
            "id": 10,
            "text": "B.배정되면 연락이 오나요",
            "norm_text": "B.배정되면 연락이 오나요",
            "speaker": {
              "id": "B",
              "sex": "여성",
              "age": "2그룹(30대~40대)"
            },
            "speechAct": "질문하기",
            "morpheme": "B/SL+./SY+배정/NNG+되/XSV+면/EC+연락/NNG+이/JKS+오/VV+나요/EC"
          },
          {
            "id": 11,
            "text": "A.네 개별통보 드리구요 통보 받는 즉시 입학등록 절차 밟으시면 됩니다",
            "norm_text": "A.네 개별통보 드리구요 통보 받는 즉시 입학등록 절차 밟으시면 됩니다",
            "speaker": {
              "id": "A",
              "sex": "여성",
              "age": "2그룹(30대~40대)"
            },
            "speechAct": "진술하기",
            "morpheme": "A/SL+네/MM+개/NNBC+별/XSN+통보/NNG+드리/VV+구요/EF+통보/NNG+받/VV+는/ETM+즉시/NNG+입학/NNG+등록/NNG+절차/NNG+밟/VV+으시/EP+면/EC+됩니다/VX+EC"
          },
          {
            "id": 12,
            "text": "B.알겠습니다 그렇게 하겠습니다",
            "norm_text": "B.알겠습니다 그렇게 하겠습니다",
            "speaker": {
              "id": "B",
              "sex": "여성",
              "age": "2그룹(30대~40대)"
            },
            "speechAct": "약속하기(개인적 수준의 서약)",
            "morpheme": "B/SL+알/VV+겠/EP+습니다/EF+그렇게/MAG+하/VV+겠/EP+습니다/EF"
          },
          {
            "id": 13,
            "text": "A.감사합니다 상담사 #@이름#였습니다",
            "norm_text": "A.감사합니다 상담사 #@이름#였습니다",
            "speaker": {
              "id": "A",
              "sex": "여성",
              "age": "2그룹(30대~40대)"
            },
            "speechAct": "인사하기",
            "morpheme": "A/SL+./SY+감사/NNG+합니다/XSV+EF+상담/NNG+사/NNG+#/SY+@/SY+이름/NNG+#/SY+였/VCP+EP+습니다/EF"
          }
        ]
      }
    }
  ]
}