{
  "dataset": {
    "identifier": 153373,
    "name": "e4_20211117_0001_1478_01",
    "src_path": "/data/file/cubeManager/PROJECT018/87/txt20211110135626085137/e4_20211117_0001_1478_01/",
    "label_path": "/data/file/cubeManager/PROJECT018/87/txt20211110135626085137/e4_20211117_0001_1478_01/",
    "category": 2,
    "type": 0
  },
  "licenses": {
    "name": "Apache License 1.0",
    "url": "http://www.apache.org/licenses/LICENSE-1.0"
  },
  "info": [
    {
      "id": 146686,
      "filename": "e4_0069_0044_02.txt",
      "title": "e4_0069_0044_02",
      "mediatype": "콜센터",
      "medianame": "콜센터",
      "category": "목적대화",
      "date": "2021-11-10",
      "size": 394,
      "annotations": {
        "subject": "일정 문의",
        "speaker_type": "1:1",
        "size": 394,
        "word_size": 89,
        "text": "A.행복한 하루 시작 #@소속# 상담원 #@이름#입니다\nB.해외에서도 #@소속# 동영상 수강이 가능한가요\nA.네 저희 #@소속# 강좌는 인터넷이 되는 곳이면 어디든지 학습 가능하세요\nB.근데 해외는 우리나라보다 인터넷이 느리잖아요\nA.예 이게 동영상 재생이다 보니까 인터넷 속도가 느리면 끊길수는 있으세요\nA.그 근처에 혹시 지인이 계시다면은 동영상 테스트를 진행해 보시겠어요\nB.네 한 번 부탁해볼게요\nA.예 스트리밍 방식이니까 미리 테스트해보시는 게 나으실 거예요\nA.워낙 해외 회선은 국가나 위치에 따라 속도가 천차만별이여서요\nB.네 그래서 좀 불안해서 전화 드렸어요\nA.네 혹시 더 궁금한 게 있으신가요\nB.아니요 이제 없어요\nA.감사합니다 #@소속# #@이름#이었습니다\nA.오늘 하루 행복한 일들만 가득하셨음 좋겠습니다",
        "lines": [
          {
            "id": 1,
            "text": "A.행복한 하루 시작 #@소속# 상담원 #@이름#입니다",
            "norm_text": "A.행복한 하루 시작 #@소속# 상담원 #@이름#입니다",
            "speaker": {
              "id": "A",
              "sex": "여성",
              "age": "3그룹(50대~60대)"
            },
            "speechAct": "인사하기",
            "morpheme": "A/SL+./SY+행복/NNG+한/XSA+ETM+하루/NNG+시작/NNG+#/SY+@/SY+소속/NNG+#/SY+상담원/NNG+#/SY+@/SY+이름/NNG+#/SY+입니다/VCP+EC"
          },
          {
            "id": 2,
            "text": "B.해외에서도 #@소속# 동영상 수강이 가능한가요",
            "norm_text": "B.해외에서도 #@소속# 동영상 수강이 가능한가요",
            "speaker": {
              "id": "B",
              "sex": "여성",
              "age": "3그룹(50대~60대)"
            },
            "speechAct": "질문하기",
            "morpheme": "B/SL+./SY+해외/NNG+에서/JKB+도/JX+#/SY+@/SY+소속/NNG+#/SY+동영상/NNG+수강/NNG+이/JKS+가능/NNG+한/XSA+ETM+가요/NNG"
          },
          {
            "id": 3,
            "text": "A.네 저희 #@소속# 강좌는 인터넷이 되는 곳이면 어디든지 학습 가능하세요",
            "norm_text": "A.네 저희 강좌는 인터넷이 되는 곳이면 어디든지 학습 가능하세요",
            "speaker": {
              "id": "A",
              "sex": "여성",
              "age": "3그룹(50대~60대)"
            },
            "speechAct": "진술하기",
            "morpheme": "A/SL+네/IC+저희/NP+#/SY+@/SY+소속/NNG+#/SY+강좌/NNG+는/JX+인터넷/NNG+이/JKS+되/VV+는/ETM+곳/NNG+이/VCP+면/EC+어디/NP+든지/VCP+EC+학습/NNG+가능/NNG+하/XSV+세요/EP+EF"
          },
          {
            "id": 4,
            "text": "B.근데 해외는 우리나라보다 인터넷이 느리잖아요",
            "norm_text": "B.근데 해외는 우리나라보다 인터넷이 느리잖아요",
            "speaker": {
              "id": "B",
              "sex": "여성",
              "age": "3그룹(50대~60대)"
            },
            "speechAct": "진술하기",
            "morpheme": "B/SL+근데/MAJ+해외/NNG+는/JX+우리/NP+나라/NNG+보다/JKB+인터넷/NNG+이/JKS+느리/VA+잖아요/EC"
          },
          {
            "id": 5,
            "text": "A.예 이게 동영상 재생이다 보니까 인터넷 속도가 느리면 끊길수는 있으세요",
            "norm_text": "A.예 이게 동영상 재생이라 인터넷 속도가 느리면 끊길 수는 있으세요",
            "speaker": {
              "id": "A",
              "sex": "여성",
              "age": "3그룹(50대~60대)"
            },
            "speechAct": "진술하기",
            "morpheme": "A/SL+예/IC+이게/NP+JKS+동영상/NNG+재생/NNG+이/VCP+다/EC+보/VX+니까/EC+인터넷/NNG+속도/NNG+가/JKS+느리/VA+면/EC+끊길/VV+ETM+수/NNB+는/JX+있/VX+으세요/EP+EP+EC"
          },
          {
            "id": 6,
            "text": "A.그 근처에 혹시 지인이 계시다면은 동영상 테스트를 진행해 보시겠어요",
            "norm_text": "A.그 근처에 혹시 지인이 계시다면은 동영상 테스트를 진행해 보시겠어요",
            "speaker": {
              "id": "A",
              "sex": "여성",
              "age": "3그룹(50대~60대)"
            },
            "speechAct": "명령하기/요구하기",
            "morpheme": "A/SL+그/MM+근처/NNG+에/JKB+혹시/MAG+지인/NNG+이/JKS+계시/VV+다면은/EC+동영상/NNG+테스트/NNG+를/JKO+진행/NNG+해/XSV+EC+보/VX+시/EP+겠/EP+어요/EF"
          },
          {
            "id": 7,
            "text": "B.네 한 번 부탁해볼게요",
            "norm_text": "B.네 한 번 부탁해볼게요",
            "speaker": {
              "id": "B",
              "sex": "여성",
              "age": "3그룹(50대~60대)"
            },
            "speechAct": "부탁하기",
            "morpheme": "B/SL+네/IC+한/MM+번/NNBC+부탁/NNG+해/XSV+EC+볼게요/VX+EF"
          },
          {
            "id": 8,
            "text": "A.예 스트리밍 방식이니까 미리 테스트해보시는 게 나으실 거예요",
            "norm_text": "A.예 스트리밍 방식이니까 미리 테스트해보시는 게 나으실 거예요",
            "speaker": {
              "id": "A",
              "sex": "여성",
              "age": "3그룹(50대~60대)"
            },
            "speechAct": "진술하기",
            "morpheme": "A/SL+예/IC+스트리밍/NNP+방식/NNG+이/VCP+니까/EC+미리/MAG+테스트/NNG+해/XSV+EC+보/VX+시/EP+는/ETM+게/NNB+JKS+나으실/VV+EP+ETM+거/NNB+예요/VCP+EF"
          },
          {
            "id": 9,
            "text": "A.워낙 해외 회선은 국가나 위치에 따라 속도가 천차만별이여서요",
            "norm_text": "A.워낙 해외 회선은 국가나 위치에 따라 속도가 천차만별이여서요",
            "speaker": {
              "id": "A",
              "sex": "여성",
              "age": "3그룹(50대~60대)"
            },
            "speechAct": "진술하기",
            "morpheme": "A/SL+워낙/MAG+해외/NNG+회선/NNG+은/JX+국가/NNG+나/JC+위치/NNG+에/JKB+따라/VV+EC+속도/NNG+가/JKS+천차만별/NNG+이/VCP+여/EC+서요/NNG"
          },
          {
            "id": 10,
            "text": "B.네 그래서 좀 불안해서 전화 드렸어요",
            "norm_text": "B.네 그래서 좀 불안해서 전화 드렸어요",
            "speaker": {
              "id": "B",
              "sex": "여성",
              "age": "3그룹(50대~60대)"
            },
            "speechAct": "진술하기",
            "morpheme": "B/SL+네/IC+그래서/MAJ+좀/MAG+불안/NNG+해서/XSV+EC+전화/NNG+드렸/VV+EP+어요/EF"
          },
          {
            "id": 11,
            "text": "A.네 혹시 더 궁금한 게 있으신가요",
            "norm_text": "A.네 혹시 더 궁금한 게 있으신가요",
            "speaker": {
              "id": "A",
              "sex": "여성",
              "age": "3그룹(50대~60대)"
            },
            "speechAct": "질문하기",
            "morpheme": "A/SL+네/IC+혹시/MAG+더/MAG+궁금/XR+한/XSA+ETM+게/NNB+JKS+있/VA+으신/EP+ETM+가요/NNG"
          },
          {
            "id": 12,
            "text": "B.아니요 이제 없어요",
            "norm_text": "B.아니요 이제 없어요",
            "speaker": {
              "id": "B",
              "sex": "여성",
              "age": "3그룹(50대~60대)"
            },
            "speechAct": "진술하기",
            "morpheme": "B/SL+아니요/IC+이제/MAG+없/VA+어요/EF"
          },
          {
            "id": 13,
            "text": "A.감사합니다 #@소속# #@이름#이었습니다",
            "norm_text": "A.감사합니다 #@소속# #@이름#이었습니다",
            "speaker": {
              "id": "A",
              "sex": "여성",
              "age": "3그룹(50대~60대)"
            },
            "speechAct": "인사하기",
            "morpheme": "A/SL+./SY+감사/NNG+합니다/XSV+EF+#/SY+@/SY+소속/NNG+#/SY+#/SY+@/SY+이름/NNG+#/SY+이/VCP+었/EP+습니다/EF"
          },
          {
            "id": 14,
            "text": "A.오늘 하루 행복한 일들만 가득하셨음 좋겠습니다",
            "norm_text": "A.오늘 하루 행복한 일들만 가득하셨음 좋겠습니다",
            "speaker": {
              "id": "A",
              "sex": "여성",
              "age": "3그룹(50대~60대)"
            },
            "speechAct": "인사하기",
            "morpheme": "A/SL+오늘/MAG+하루/NNG+행복/NNG+한/XSA+ETM+일/NNG+들/XSN+만/JX+가득/MAG+하/VV+셨/EP+EP+음/ETN+좋/VA+겠/EP+습니다/EF"
          }
        ]
      }
    }
  ]
}